awss3gonla/__init__.py
awss3gonla/client.py
awss3gonla/storage.py
awss3gonla-1.0.0.dist-info/METADATA
awss3gonla-1.0.0.dist-info/WHEEL
awss3gonla-1.0.0.dist-info/top_level.txt
awss3gonla-1.0.0.dist-info/RECORD
