Metadata-Version: 2.1
Name: awss3gonla
Version: 1.0.0
Summary: The `awss3gonla` class provides a Python interface for interacting with AWS S3 storage. It allows for operations such as uploading and downloading files, managing parquet files, and handling data partitions. This class is designed to work with the AWS SDK for Python (`boto3`) and the Polars library for data manipulation.
Home-page: https://github.com/leonardogonzalolaura/workspace_libraries
Author: Leonardo Daniel Gonzalo Laura
Author-email: glleonardodaniel@gmail.com
License: MIT
Requires-Dist: boto3
Requires-Dist: polars
Requires-Dist: rich
